README.md
setup.cfg
setup.py
wuutils/__init__.py
wuutils/wuutils.py
wuutils.egg-info/PKG-INFO
wuutils.egg-info/SOURCES.txt
wuutils.egg-info/dependency_links.txt
wuutils.egg-info/requires.txt
wuutils.egg-info/top_level.txt