Metadata-Version: 1.0
Name: wuutils
Version: 0.0.19
Summary: Dumb utility functions I use
Home-page: http://github.com/sirrice/wuutils
Author: Eugene Wu
Author-email: ewu@cs.columbia.edu
License: MIT
Platform: UNKNOWN
